{"ajId": "8e7fccef-d7c2-4a7a-8740-3c3b8ce1a204", "ajName": "董兴伟强奸罪一案", "ajjbqk": " 四川省旺苍县人民检察院指控，2017年3月27日，被害人侯某（女，15岁）在被告人董兴伟处借用一部苹果5s手机，后欲将该手机据为已有，谎称手机被老师没收，进而答应被告人董兴伟提出用三次性关系交换手机的要求。5月28日，被害人侯某第一次在被告人董兴伟位于旺苍县东河镇五峰村五峰巷69号的家中卧室与其发生性关系后，明确表示不想再与其发生性关系，被告人董兴伟便以公开张贴聊天记录、到校找被害人侯某麻烦、告知被害人侯某母亲等方式相胁迫，要求被害人侯某与其再次发生性关系。被害人侯某被迫于5月30日来到被告人董兴伟的家中与其发生性关系，在发生性关系过程中，被害人侯某抵抗、哭闹，明确表示不愿意与被告人董兴伟继续发生性关系，被告人董兴伟采用捂嘴、掰腿等方式，强行与被害人继续发生了性关系。后被告人董兴伟再次胁迫被害人要求发生第三次性关系，被害人侯某被迫报警。 公诉机关认为，被告人董兴伟使用胁迫、暴力手段强奸妇女，其行为已构成强奸罪。被告人董兴伟到案后，如实供述自己的罪行，系坦白。应依照《中华人民共和国刑法》第二百三十六条第一款、第六十七条第三款之规定，追究其刑事责任。 被告人董兴伟对公诉机关指控的犯罪事实供认不讳，请求从处罚。 辩护人何勇卫提出，事情的起因是被害人侯某导致的。被告人董兴伟到案后认罪伏法，建议对其从轻处罚并适用缓刑。 本院审理查明被告人董兴伟的犯罪事实与公诉机关指控的犯罪事实一致。 上述事实被告人董兴伟在开庭审理过程中无异议，且有受案登记表、立案决定书；被告人董兴伟的基本情况和户籍证明；旺苍县公安局西城派出所及民警杨某、陈某出具的到案经过和情况说明；人身安全检查笔录、扣押决定书、扣押笔录、扣押清单；被告人董兴伟的手机信息、手机聊天记录、封存电子证据清单；被害人侯某的陈述；刑侦照片、现场勘验检查工作笔录、电子证据检查笔录、鉴定意见书等证据证实，足以认定。 ", "cpfxgc": "本院认为，被告人董兴伟违背妇女意志，使用暴力、胁迫手段与妇女发生性关系，其行为已构成强奸罪，公诉机关指控的犯罪事实清楚，证据确实、充分，罪名经庭审确认成立。辩护人何勇卫提出，事情的起因是被害人侯某导致的主张，与被害人侯某遭被告人董兴伟强奸，不存在必然的因果关系，其主张本院不予采纳。辩护人何勇卫还提出，被告人董兴伟到案后认罪伏法，建议从轻处罚，并适用缓刑。经查，被告人董兴伟到案后认罪伏法属实，可以从轻处罚，但建议对其适用缓刑的意见，本院不予采纳。依照《中华人民共和国刑法》第二百三十六条第一款，第六十七条第三款的规定，判决如下：", "pjjg": " 被告人董兴伟犯强奸罪，判处有期徒刑三年。 （刑期从判决执行之日起计算。判决前先行羁押的，羁押一日折抵刑期一日，即从2018年8月30日至2021年8月29日止。） 如不服本判决，可在接到判决书的第二日起十日内，通过本院或者直接向广元市中级人民法院提起上诉。书面上诉的，应当提交上诉状正本一份，副本二份。", "qw": "四川省旺苍县人民法院 刑事判决书 （2018）川0821刑初126号 公诉机关四川省旺苍县人民检察院。 被告人董兴伟，男，生于1993年12月1日，汉族，四川省旺苍县人，中专文化，工人，住旺苍县。因涉嫌强奸罪，于2017年5月30日被旺苍县公安局监视居住。2018年8月30日被依法逮捕，现羁押于旺苍县看守所。 辩护人何勇卫，四川新伦律师事务所律师。 四川省旺苍县人民检察院以旺检公刑诉（2018）85号起诉书指控被告人董兴伟犯强奸罪，于2018年8月7日向本院提起公诉。本院依法组成合议庭，不公开开庭审理了本案。旺苍县人民检察院指派检察员李双宝出庭支持公诉。被告人董兴伟及其辩护人何勇卫到庭参加诉讼。现已审理终结。 四川省旺苍县人民检察院指控，2017年3月27日，被害人侯某（女，15岁）在被告人董兴伟处借用一部苹果5s手机，后欲将该手机据为已有，谎称手机被老师没收，进而答应被告人董兴伟提出用三次性关系交换手机的要求。5月28日，被害人侯某第一次在被告人董兴伟位于旺苍县东河镇五峰村五峰巷69号的家中卧室与其发生性关系后，明确表示不想再与其发生性关系，被告人董兴伟便以公开张贴聊天记录、到校找被害人侯某麻烦、告知被害人侯某母亲等方式相胁迫，要求被害人侯某与其再次发生性关系。被害人侯某被迫于5月30日来到被告人董兴伟的家中与其发生性关系，在发生性关系过程中，被害人侯某抵抗、哭闹，明确表示不愿意与被告人董兴伟继续发生性关系，被告人董兴伟采用捂嘴、掰腿等方式，强行与被害人继续发生了性关系。后被告人董兴伟再次胁迫被害人要求发生第三次性关系，被害人侯某被迫报警。 公诉机关认为，被告人董兴伟使用胁迫、暴力手段强奸妇女，其行为已构成强奸罪。被告人董兴伟到案后，如实供述自己的罪行，系坦白。应依照《中华人民共和国刑法》第二百三十六条第一款、第六十七条第三款之规定，追究其刑事责任。 被告人董兴伟对公诉机关指控的犯罪事实供认不讳，请求从处罚。 辩护人何勇卫提出，事情的起因是被害人侯某导致的。被告人董兴伟到案后认罪伏法，建议对其从轻处罚并适用缓刑。 本院审理查明被告人董兴伟的犯罪事实与公诉机关指控的犯罪事实一致。 上述事实被告人董兴伟在开庭审理过程中无异议，且有受案登记表、立案决定书；被告人董兴伟的基本情况和户籍证明；旺苍县公安局西城派出所及民警杨某、陈某出具的到案经过和情况说明；人身安全检查笔录、扣押决定书、扣押笔录、扣押清单；被告人董兴伟的手机信息、手机聊天记录、封存电子证据清单；被害人侯某的陈述；刑侦照片、现场勘验检查工作笔录、电子证据检查笔录、鉴定意见书等证据证实，足以认定。 本院认为，被告人董兴伟违背妇女意志，使用暴力、胁迫手段与妇女发生性关系，其行为已构成强奸罪，公诉机关指控的犯罪事实清楚，证据确实、充分，罪名经庭审确认成立。辩护人何勇卫提出，事情的起因是被害人侯某导致的主张，与被害人侯某遭被告人董兴伟强奸，不存在必然的因果关系，其主张本院不予采纳。辩护人何勇卫还提出，被告人董兴伟到案后认罪伏法，建议从轻处罚，并适用缓刑。经查，被告人董兴伟到案后认罪伏法属实，可以从轻处罚，但建议对其适用缓刑的意见，本院不予采纳。依照《中华人民共和国刑法》第二百三十六条第一款，第六十七条第三款的规定，判决如下： 被告人董兴伟犯强奸罪，判处有期徒刑三年。 （刑期从判决执行之日起计算。判决前先行羁押的，羁押一日折抵刑期一日，即从2018年8月30日至2021年8月29日止。） 如不服本判决，可在接到判决书的第二日起十日内，通过本院或者直接向广元市中级人民法院提起上诉。书面上诉的，应当提交上诉状正本一份，副本二份。 审判长周建波 人民陪审员李力 人民陪审员冯光学 二〇一八年九月五日 书记员李钊 附相关法律条文： 《中华人民共和国刑法》 第二百三十六条［强奸罪］以暴力、胁迫或者其他手段强奸妇女的，处三年以上十年以下有期徒刑。 奸淫不满十四周岁的幼女的，以强奸论，从重处罚。 强奸妇女、奸淫幼女，有下列情形之一的，处十年以上有期徒刑、无期徒刑或者死刑： （一）强奸妇女、奸淫幼女情节恶劣的； （二）强奸妇女、奸淫幼女多人的； （三）在公共场所当众强奸妇女的； （四）二人以上轮奸的； （五）致使被害人重伤、死亡或者造成其他严重后果的。 第六十七条［自首］犯罪以后自动投案，如实供述自己的罪行的，是自首。对于自首的犯罪分子，可以从轻或者减轻处罚。其中，犯罪较轻的，可以免除处罚。 被采取强制措施的犯罪嫌疑人、被告人和正在服刑的罪犯，如实供述司法机关还未掌握的本人其他罪行的，以自首论。 犯罪嫌疑人虽不具有前两款规定的自首情节，但是如实供述自己罪行的，可以从轻处罚；因其如实供述自己罪行，避免特别严重后果发生的，可以减轻处罚。”", "writId": "047838d62b5f7011c9ee5dc4f96c29b3438", "writName": "董兴伟强奸罪一审刑事判决书", "inputs": {"input_ids": [1724, 2335, 4689, 3200, 5721, 1344, 782, 3696, 3466, 2175, 7368, 2900, 2971, 8024, 8109, 2399, 124, 3299, 8149, 3189, 8024, 6158, 2154, 782, 908, 3378, 8020, 1957, 8024, 8115, 2259, 8021, 1762, 6158, 1440, 782, 5869, 1069, 836, 1905, 955, 4500, 671, 6956, 5741, 3362, 9376, 2797, 3322, 8024, 1400, 3617, 2199, 6421, 2797, 3322, 2945, 711, 2347, 3300, 8024, 6453, 4917, 2797, 3322, 6158, 5439, 2360, 3766, 3119, 8024, 6822, 5445, 5031, 2418, 6158, 1440, 782, 5869, 1069, 836, 2990, 1139, 4500, 676, 3613, 2595, 1068, 5143, 769, 2940, 2797, 3322, 4638, 6206, 3724, 511, 126, 3299, 8143, 3189, 8024, 6158, 2154, 782, 908, 3378, 5018, 671, 3613, 1762, 6158, 1440, 782, 5869, 1069, 836, 855, 754, 3200, 5721, 1344, 691, 3777, 7252, 758, 2292, 3333, 758, 2292, 2350, 8419, 1384, 4638, 2157, 704, 1309, 2147, 680, 1071, 1355, 4495, 2595, 1068, 5143, 1400, 8024, 3209, 4802, 6134, 4850, 679, 2682, 1086, 680, 1071, 1355, 4495, 2595, 1068, 5143, 8024, 6158, 1440, 782, 5869, 1069, 836, 912, 809, 1062, 2458, 2476, 6585, 5464, 1921, 6381, 2497, 510, 1168, 3413, 2823, 6158, 2154, 782, 908, 3378, 7937, 4172, 510, 1440, 4761, 6158, 2154, 782, 908, 3378, 3678, 779, 5023, 3175, 2466, 4685, 5516, 6833, 8024, 6206, 3724, 6158, 2154, 782, 908, 3378, 680, 1071, 1086, 3613, 1355, 4495, 2595, 1068, 5143, 511, 6158, 2154, 782, 908, 3378, 6158, 6833, 754, 126, 3299, 8114, 3189, 3341, 1168, 6158, 1440, 782, 5869, 1069, 836, 4638, 2157, 704, 680, 1071, 1355, 4495, 2595, 1068, 5143, 8024, 1762, 1355, 4495, 2595, 1068, 5143, 6814, 4923, 704, 8024, 6158, 2154, 782, 908, 3378, 2850, 2834, 510, 1526, 7317, 8024, 3209, 4802, 6134, 4850, 679, 2703, 2692, 680, 6158, 1440, 782, 5869, 1069, 836, 5326, 5330, 1355, 4495, 2595, 1068, 5143, 8024, 6158, 1440, 782, 5869, 1069, 836, 7023, 4500, 2926, 1673, 510, 2976, 5597, 5023, 3175, 2466, 8024, 2487, 6121, 680, 6158, 2154, 782, 5326, 5330, 1355, 4495, 749, 2595, 1068, 5143, 511, 1400, 6158, 1440, 782, 5869, 1069, 836, 1086, 3613, 5516, 6833, 6158, 2154, 782, 6206, 3724, 1355, 4495, 5018, 676, 3613, 2595, 1068, 5143, 8024, 6158, 2154, 782, 908, 3378, 6158, 6833, 2845, 6356, 511, 1062, 6401, 3322, 1068, 6371, 711, 8024, 6158, 1440, 782, 5869, 1069, 836, 886, 4500, 5516, 6833, 510, 3274, 1213, 2797, 3667, 2487, 1960, 1967, 1957, 8024, 1071, 6121, 711, 2347, 3354, 2768, 2487, 1960, 5389, 511, 6158, 1440, 782, 5869, 1069, 836, 1168, 3428], "event_type_ids": [0, 0, 0, 0, 0, 0, 0, 0, 0, 0, 0, 0, 0, 0, 0, 0, 0, 0, 0, 0, 0, 0, 0, 0, 0, 0, 0, 0, 0, 0, 0, 0, 0, 0, 0, 0, 0, 0, 0, 0, 22, 0, 0, 0, 0, 0, 0, 0, 0, 0, 0, 0, 0, 0, 0, 0, 80, 0, 0, 0, 0, 71, 0, 0, 0, 0, 0, 0, 9, 0, 0, 0, 0, 47, 0, 0, 0, 0, 0, 0, 0, 51, 0, 0, 0, 0, 0, 0, 0, 0, 0, 0, 0, 0, 50, 50, 0, 0, 0, 0, 0, 0, 0, 0, 0, 0, 0, 0, 0, 0, 0, 0, 0, 0, 0, 0, 0, 0, 0, 0, 0, 0, 0, 0, 0, 0, 0, 0, 0, 0, 0, 0, 0, 0, 0, 0, 0, 0, 0, 0, 0, 0, 83, 0, 0, 0, 0, 0, 0, 0, 0, 0, 0, 0, 0, 0, 0, 0, 83, 0, 0, 0, 0, 0, 0, 0, 0, 0, 0, 0, 0, 0, 0, 0, 0, 0, 0, 0, 0, 0, 0, 0, 0, 0, 0, 0, 0, 0, 0, 0, 37, 0, 0, 0, 0, 0, 0, 0, 0, 0, 0, 0, 67, 67, 67, 0, 50, 50, 0, 0, 0, 0, 0, 0, 0, 0, 0, 0, 0, 83, 0, 0, 0, 0, 0, 0, 0, 0, 0, 67, 0, 0, 0, 0, 0, 0, 0, 0, 0, 0, 0, 0, 0, 0, 0, 0, 0, 0, 0, 0, 83, 0, 0, 0, 0, 0, 0, 83, 0, 0, 0, 0, 0, 0, 0, 0, 0, 0, 0, 48, 48, 0, 0, 0, 0, 0, 0, 0, 0, 0, 47, 0, 0, 0, 0, 0, 0, 0, 0, 0, 0, 0, 0, 83, 0, 0, 0, 0, 0, 0, 0, 0, 0, 0, 0, 0, 0, 0, 0, 0, 0, 0, 0, 0, 67, 0, 0, 0, 0, 0, 0, 0, 0, 0, 0, 83, 0, 0, 0, 0, 0, 0, 0, 0, 0, 0, 0, 0, 67, 67, 0, 0, 0, 50, 50, 0, 0, 0, 0, 0, 83, 0, 0, 0, 0, 0, 0, 0, 0, 0, 0, 12, 0, 0, 0, 0, 0, 0, 0, 0, 0, 0, 0, 0, 0, 0, 0, 0, 0, 67, 0, 0, 62, 0, 0, 0, 83, 83, 0, 0, 0, 0, 0, 0, 0, 0, 0, 0, 0, 0, 0, 0, 0, 0, 0, 0, 0, 0, 0]}}