{"ajId": "08f8ad93-000d-4c6f-a571-d3aa03bd360c", "ajName": "郑季平走私、贩卖、运输、制造毒品罪一案", "ajjbqk": " 福州市鼓楼区人民检察院指控：2018年7月15日20时许，被告人郑季平在福州市鼓楼区澳门桥附近将49.7克大麻以3750元人民币的价格卖与陈某（另案处理），交易完成后被告人郑季平被公安机关当场抓获。 公诉机关认为，被告人郑季平的行为构成贩卖毒品罪。因被告人郑季平如实供述自己的罪行，建议判处被告人郑季平有期徒刑六个月，并处罚金人民币二千元。 被告人郑季平对公诉机关指控事实供认不讳。 以上事实有涉案毒品照片；福州市公安局南街派出所出具的扣押清单、抓获经过、户籍证明、福州市公安局鼓楼分局禁毒大队出具的福建省毒品实物缴交收据、福建省毒品案件样品留存收据；证人陈某的证言；被告人郑季平的供述与辩解；福建正中司法鉴定所司法鉴定意见书；福州市公安局南街派出所出具的提取笔录、扣押笔录，被告人郑季平对证人陈某、作案地点、毒品、微信聊天内容及支付宝转账记录的辨认，证人陈某对被告郑季平、交易地点、毒品、微信聊天内容及支付宝转账记录的辨认等其他证据材料证实，足以认定。 ", "cpfxgc": "本院认为，被告人郑季平违反国家对毒品的管理法规，贩卖大麻49.7克，其行为已构成贩卖毒品罪，公诉机关指控被告人郑季平的罪名成立。被告人郑季平如实供述自己的罪行，可以从轻处罚。根据《中华人民共和国刑法》第三百四十七条第一款、第四款，第六十七条第三款、第六十四条之规定，判决如下：", "pjjg": " 一、被告人郑季平犯贩卖毒品罪，判处有期徒刑六个月，并处罚金人民币二千元。 （刑期从判决执行之日起计算。判决执行以前先行羁押的，羁押一日折抵刑期一日，即自2018年7月16日起至2019年1月15日止。罚金应于判决生效次日起三个月内缴纳。） 二、扣押在案的毒资人民币3750元予以没收，上缴国库（由扣押单位负责执行）。 如不服本判决，可在接到判决书的第二日起十日内，通过本院或直接向福建省福州市中级人民法院提出上诉。书面上诉的，应当提交上诉状正本一份，副本二份。", "qw": "福建省福州市鼓楼区人民法院 刑事判决书 （2018）闽0102刑初716号 公诉机关福州市鼓楼区人民检察院。 被告人郑季平，男，1992年12月23日出生，汉族，初中文化程度，个体经营者，出生地福建省福清市，户籍所在地福建省福清市，现住福建省连江县。2018年7月16日因涉嫌贩卖毒品罪被刑事拘留，同年7月25日被执行逮捕。现羁押于福州市第一看守所。 福州市鼓楼区人民检察院以鼓检公诉刑诉（2018）720号起诉书指控被告人郑季平犯贩卖毒品罪，于2018年9月18日向本院提起公诉。本院依法适用简易程序，实行独任审判，公开开庭审理了本案。福州市鼓楼区人民检察院指派检察员郑某出庭支持公诉，被告人郑季平到庭参加诉讼，现已审理终结。 福州市鼓楼区人民检察院指控：2018年7月15日20时许，被告人郑季平在福州市鼓楼区澳门桥附近将49.7克大麻以3750元人民币的价格卖与陈某（另案处理），交易完成后被告人郑季平被公安机关当场抓获。 公诉机关认为，被告人郑季平的行为构成贩卖毒品罪。因被告人郑季平如实供述自己的罪行，建议判处被告人郑季平有期徒刑六个月，并处罚金人民币二千元。 被告人郑季平对公诉机关指控事实供认不讳。 以上事实有涉案毒品照片；福州市公安局南街派出所出具的扣押清单、抓获经过、户籍证明、福州市公安局鼓楼分局禁毒大队出具的福建省毒品实物缴交收据、福建省毒品案件样品留存收据；证人陈某的证言；被告人郑季平的供述与辩解；福建正中司法鉴定所司法鉴定意见书；福州市公安局南街派出所出具的提取笔录、扣押笔录，被告人郑季平对证人陈某、作案地点、毒品、微信聊天内容及支付宝转账记录的辨认，证人陈某对被告郑季平、交易地点、毒品、微信聊天内容及支付宝转账记录的辨认等其他证据材料证实，足以认定。 本院认为，被告人郑季平违反国家对毒品的管理法规，贩卖大麻49.7克，其行为已构成贩卖毒品罪，公诉机关指控被告人郑季平的罪名成立。被告人郑季平如实供述自己的罪行，可以从轻处罚。根据《中华人民共和国刑法》第三百四十七条第一款、第四款，第六十七条第三款、第六十四条之规定，判决如下： 一、被告人郑季平犯贩卖毒品罪，判处有期徒刑六个月，并处罚金人民币二千元。 （刑期从判决执行之日起计算。判决执行以前先行羁押的，羁押一日折抵刑期一日，即自2018年7月16日起至2019年1月15日止。罚金应于判决生效次日起三个月内缴纳。） 二、扣押在案的毒资人民币3750元予以没收，上缴国库（由扣押单位负责执行）。 如不服本判决，可在接到判决书的第二日起十日内，通过本院或直接向福建省福州市中级人民法院提出上诉。书面上诉的，应当提交上诉状正本一份，副本二份。 审判员毛岚岚 二〇一八年九月二十七日 书记员林文豪 附：本案判决依据的主要法律条文 1、《中华人民共和国刑法》第三百四十七条第一款、第四款 走私、贩卖、运输、制造毒品，无论数量多少，都应当追究刑事责任，予以刑事处罚。 走私、贩卖、运输、制造鸦片不满二百克、海洛因或者甲基苯丙胺不满十克或者其他少量毒品的，处三年以下有期徒刑、拘役（。http：。／。。／。china．findlaw．cn。／。bianhu。／。xingfazhonglei。／。juyi。／。_blank。）或者管制（。http：。／。。／。china．findlaw．cn。／。bianhu。／。xingfazhonglei。／。guanzhi。／。_blank。），并处罚金；情节严重的，处三年以上七年以下有期徒刑，并处罚金。 2、《中华人民共和国刑法》第六十七条第三款 犯罪嫌疑人虽不具有前两款规定的自首情节，但是如实供述自己罪行的，可以从轻处罚；因其如实供述自己罪行，避免特别严重后果发生的，可以减轻处罚。 3、《中华人民共和国刑法》第六十四条 犯罪分子违法所得的一切财物，应当予以追缴或者责令退赔；对被害人的合法财产，应当及时返还；违禁品和供犯罪所用的本人财物，应当予以没收。没收的财物和罚金，一律上缴国库，不得挪用和自行处理。", "writId": "04622990ed0d5fd8173ba5e919454f1606d", "writName": "郑季平走私、贩卖、运输、制造毒品罪一审刑事判决书", "inputs": {"input_ids": [4886, 2336, 2356, 7961, 3517, 1277, 782, 3696, 3466, 2175, 7368, 2900, 2971, 8038, 8271, 2399, 128, 3299, 8115, 3189, 8113, 3198, 6387, 8024, 6158, 1440, 782, 6948, 2108, 2398, 1762, 4886, 2336, 2356, 7961, 3517, 1277, 4078, 7305, 3441, 7353, 6818, 2199, 8249, 119, 128, 1046, 1920, 7937, 809, 11256, 8129, 1039, 782, 3696, 2355, 4638, 817, 3419, 1297, 680, 7357, 3378, 8020, 1369, 3428, 1905, 4415, 8021, 8024, 769, 3211, 2130, 2768, 1400, 6158, 1440, 782, 6948, 2108, 2398, 6158, 1062, 2128, 3322, 1068, 2496, 1767, 2831, 5815, 511, 1062, 6401, 3322, 1068, 6371, 711, 8024, 6158, 1440, 782, 6948, 2108, 2398, 4638, 6121, 711, 3354, 2768, 6575, 1297, 3681, 1501, 5389, 511, 1728, 6158, 1440, 782, 6948, 2108, 2398, 1963, 2141, 897, 6835, 5632, 2346, 4638, 5389, 6121, 8024, 2456, 6379, 1161, 1905, 6158, 1440, 782, 6948, 2108, 2398, 3300, 3309, 2530, 1152, 1063, 702, 3299, 8024, 2400, 1905, 5385, 7032, 782, 3696, 2355, 753, 1283, 1039, 511, 6158, 1440, 782, 6948, 2108, 2398, 2190, 1062, 6401, 3322, 1068, 2900, 2971, 752, 2141, 897, 6371, 679, 6383, 511, 809, 677, 752, 2141, 3300, 3868, 3428, 3681, 1501, 4212, 4275, 8039, 4886, 2336, 2356, 1062, 2128, 2229, 1298, 6125, 3836, 1139, 2792, 1139, 1072, 4638, 2807, 2852, 3926, 1296, 510, 2831, 5815, 5307, 6814, 510, 2787, 5093, 6395, 3209, 510, 4886, 2336, 2356, 1062, 2128, 2229, 7961, 3517, 1146, 2229, 4881, 3681, 1920, 7339, 1139, 1072, 4638, 4886, 2456, 4689, 3681, 1501, 2141, 4289, 5373, 769, 3119, 2945, 510, 4886, 2456, 4689, 3681, 1501, 3428, 816, 3416, 1501, 4522, 2100, 3119, 2945, 8039, 6395, 782, 7357, 3378, 4638, 6395, 6241, 8039, 6158, 1440, 782, 6948, 2108, 2398, 4638, 897, 6835, 680, 6796, 6237, 8039, 4886, 2456, 3633, 704, 1385, 3791, 7063, 2137, 2792, 1385, 3791, 7063, 2137, 2692, 6224, 741, 8039, 4886, 2336, 2356, 1062, 2128, 2229, 1298, 6125, 3836, 1139, 2792, 1139, 1072, 4638, 2990, 1357, 5011, 2497, 510, 2807, 2852, 5011, 2497, 8024, 6158, 1440, 782, 6948, 2108, 2398, 2190, 6395, 782, 7357, 3378, 510, 868, 3428, 1765, 4157, 510, 3681, 1501, 510, 2544, 928, 5464, 1921, 1079, 2159, 1350, 3118, 802, 2140, 6760, 6572, 6381, 2497, 4638, 6795, 6371, 8024, 6395, 782, 7357, 3378, 2190, 6158, 1440, 6948, 2108, 2398, 510, 769, 3211, 1765, 4157, 510, 3681, 1501, 510, 2544, 928, 5464, 1921, 1079, 2159, 1350, 3118, 802, 2140, 6760, 6572, 6381, 2497, 4638, 6795, 6371, 5023, 1071, 800, 6395, 2945, 3332, 3160, 6395], "event_type_ids": [0, 0, 0, 0, 0, 0, 0, 0, 0, 0, 0, 0, 0, 0, 0, 0, 0, 0, 0, 0, 0, 0, 0, 0, 0, 0, 0, 0, 0, 0, 0, 0, 0, 0, 0, 0, 0, 0, 0, 0, 0, 0, 0, 0, 0, 0, 0, 0, 0, 0, 0, 0, 0, 0, 0, 0, 0, 0, 0, 87, 0, 0, 0, 0, 0, 0, 0, 0, 0, 0, 17, 17, 0, 0, 0, 0, 0, 0, 0, 0, 0, 0, 0, 0, 0, 0, 0, 0, 11, 0, 0, 0, 0, 0, 0, 0, 0, 0, 0, 0, 0, 0, 0, 0, 0, 0, 0, 0, 0, 87, 0, 0, 0, 0, 0, 0, 0, 0, 0, 0, 0, 0, 0, 0, 3, 0, 0, 0, 0, 0, 0, 0, 51, 0, 0, 0, 0, 0, 0, 0, 0, 0, 0, 0, 0, 0, 0, 0, 0, 0, 0, 0, 0, 0, 0, 0, 0, 0, 0, 0, 0, 0, 0, 0, 0, 0, 0, 0, 0, 0, 0, 0, 0, 0, 0, 0, 3, 0, 0, 0, 0, 0, 0, 0, 0, 0, 0, 0, 0, 0, 0, 0, 0, 0, 0, 0, 0, 0, 0, 0, 0, 0, 0, 0, 0, 0, 0, 9, 0, 0, 0, 0, 11, 0, 0, 0, 0, 0, 0, 0, 0, 0, 0, 0, 0, 0, 0, 0, 0, 0, 0, 0, 0, 0, 0, 0, 0, 0, 0, 0, 0, 0, 0, 0, 0, 0, 0, 0, 0, 0, 0, 0, 0, 0, 0, 0, 0, 0, 0, 0, 0, 0, 0, 0, 0, 0, 0, 0, 0, 0, 0, 0, 0, 0, 0, 0, 0, 0, 0, 0, 3, 0, 0, 0, 0, 0, 0, 0, 0, 0, 0, 0, 0, 0, 0, 0, 0, 13, 0, 0, 0, 0, 0, 0, 0, 0, 0, 0, 0, 0, 0, 0, 0, 0, 0, 0, 0, 0, 0, 0, 0, 0, 9, 0, 0, 0, 0, 0, 0, 0, 0, 0, 0, 0, 0, 0, 0, 0, 0, 0, 0, 0, 0, 0, 0, 0, 0, 0, 0, 0, 0, 0, 0, 0, 0, 0, 0, 28, 0, 0, 0, 0, 0, 0, 0, 0, 0, 0, 0, 0, 0, 0, 0, 0, 0, 0, 17, 0, 0, 0, 0, 0, 0, 0, 0, 0, 0, 0, 0, 0, 0, 0, 0, 0, 28, 0, 0, 0, 0, 0, 0, 0, 0, 0, 0, 0, 0, 0, 0]}}