{"ajId": "5749d520-990a-4381-bfe0-e3a9ff98bed8", "ajName": "王兴毕盗窃一案", "ajjbqk": " 云南省宣威市人民检察院指控，2018年11月6日10时50分许，被告人王兴毕在一辆由宣威市新北站开往宣威市虹桥街道的4路公交车上，用随身携带的刀片划开乘客蒋某1能的外衣左侧衣袋，盗走人民币1300元，后王兴毕在街心花园站台下车时被宣威市公安局民警抓获。案发后，被盗人民币1300元已追回并发还被害人蒋某1能。公诉机关列举了物证、书证、被害人陈述、被告人的供述与辩解、辨认笔录等证实指控的事实，并认为被告人王兴毕以非法占有为目的，在公共场所扒窃他人财物，其行为触犯《中华人民共和国刑法》第二百六十四条之规定，应当以盗窃罪追究其刑事责任；王兴毕曾因犯盗窃罪被判处有期徒刑以上刑罚，刑罚执行完毕以后，在五年内再犯有期徒刑以上刑罚之罪，是累犯，适用《中华人民共和国刑法》第六十五条之规定；王兴毕到案后能如实供述自己的罪行，系坦白，适用《中华人民共和国刑法》第六十七条第三款之规定。庭审中，建议判处其一年六个月以下有期徒刑，并处罚金。 被告人王兴毕对公诉机关的指控无异议，请求从轻处罚。 经审理查明，2018年11月6日10时50分许，被告人王兴毕在由宣威市新北站开往宣威市虹桥街道的4路公交车上，用随身携带的刀片划开乘客蒋某1能的外衣左侧衣袋，盗走人民币1300元，后王兴毕在街心花园站台下车时被宣威市公安局民警抓获。案发后，被盗人民币1300元已追回并发还被害人蒋某1能。 上述事实，被告人在庭审中亦无异议，且有公诉机关提交并经法庭质证认证的接处警登记表，受案登记表，立案决定书，被害人蒋某1能的陈述记录，辨认笔录及照片，提取笔录及照片，扣押笔录及照片，发还清单，刑事判决书，释放证明，户口证明，抓获经过等证据与被告人王兴毕的供述记录相互印证，予以证实。 ", "cpfxgc": "本院认为，被告人王兴毕以非法占有为目的，在公共场所扒窃他人财物，其行为侵犯了公私财物的所有权，已构成盗窃罪。公诉机关的指控成立。被告人王兴毕曾因犯盗窃罪被判处有期徒刑以上刑罚，刑罚执行完毕五年内再犯应当判处有期徒刑以上刑罚之罪，系累犯，依法应从重处罚并不适用缓刑，其归案后能如实供述犯罪事实，系坦白，依法可从轻处罚；案发后，被盗财物已追回并发还被害人，对其可酌情从轻处罚。公诉机关的量刑建议，本院予以采纳。据此，依照《中华人民共和国刑法》第二百六十四条，第六十五条第一款，第七十四条，第六十七条第三款，第五十二条，第五十三第一款之规定，判决如下：", "pjjg": " 被告人王兴毕犯盗窃罪，判处有期徒刑八个月，并处罚金人民币2500元（于判决生效后三个月内缴纳）。 （刑期从判决执行之日起计算，判决执行以前先行羁押的，羁押一日折抵刑期一日，即自2018年11月6日起至2019年7月5日止）。 如不服本判决，可在接到判决书的第二日起十日内，通过本院或者直接向云南省曲靖市中级人民法院提出上诉。书面上诉的，应当提交上诉状正本一份，副本二份。", "qw": "云南省宣威市人民法院 刑事判决书 （2019）云0381刑初23号 公诉机关云南省宣威市人民检察院。 被告人王兴毕，男，1966年10月5日生，汉族，小学文化，农民，云南省会泽县人，住宣威市，因犯盗窃罪于2015年3月12日被宣威市人民法院判处有期徒刑六个月，并处罚金人民币2000元，2015年6月9日刑满释放。现因涉嫌盗窃罪，于2018年11月6日被刑事拘留，同年11月17日执行逮捕。羁押于宣威市看守所。 云南省宣威市人民检察院以宣检公诉刑诉［2018］472号起诉书指控被告人王兴毕犯盗窃罪，于2019年1月2日向本院提起公诉。本院依法组成合议庭，公开开庭审理了本案。宣威市人民检察院指派检察员宁显章出庭支持公诉，被告人王兴毕到庭参加诉讼。现已审理终结。 云南省宣威市人民检察院指控，2018年11月6日10时50分许，被告人王兴毕在一辆由宣威市新北站开往宣威市虹桥街道的4路公交车上，用随身携带的刀片划开乘客蒋某1能的外衣左侧衣袋，盗走人民币1300元，后王兴毕在街心花园站台下车时被宣威市公安局民警抓获。案发后，被盗人民币1300元已追回并发还被害人蒋某1能。公诉机关列举了物证、书证、被害人陈述、被告人的供述与辩解、辨认笔录等证实指控的事实，并认为被告人王兴毕以非法占有为目的，在公共场所扒窃他人财物，其行为触犯《中华人民共和国刑法》第二百六十四条之规定，应当以盗窃罪追究其刑事责任；王兴毕曾因犯盗窃罪被判处有期徒刑以上刑罚，刑罚执行完毕以后，在五年内再犯有期徒刑以上刑罚之罪，是累犯，适用《中华人民共和国刑法》第六十五条之规定；王兴毕到案后能如实供述自己的罪行，系坦白，适用《中华人民共和国刑法》第六十七条第三款之规定。庭审中，建议判处其一年六个月以下有期徒刑，并处罚金。 被告人王兴毕对公诉机关的指控无异议，请求从轻处罚。 经审理查明，2018年11月6日10时50分许，被告人王兴毕在由宣威市新北站开往宣威市虹桥街道的4路公交车上，用随身携带的刀片划开乘客蒋某1能的外衣左侧衣袋，盗走人民币1300元，后王兴毕在街心花园站台下车时被宣威市公安局民警抓获。案发后，被盗人民币1300元已追回并发还被害人蒋某1能。 上述事实，被告人在庭审中亦无异议，且有公诉机关提交并经法庭质证认证的接处警登记表，受案登记表，立案决定书，被害人蒋某1能的陈述记录，辨认笔录及照片，提取笔录及照片，扣押笔录及照片，发还清单，刑事判决书，释放证明，户口证明，抓获经过等证据与被告人王兴毕的供述记录相互印证，予以证实。 本院认为，被告人王兴毕以非法占有为目的，在公共场所扒窃他人财物，其行为侵犯了公私财物的所有权，已构成盗窃罪。公诉机关的指控成立。被告人王兴毕曾因犯盗窃罪被判处有期徒刑以上刑罚，刑罚执行完毕五年内再犯应当判处有期徒刑以上刑罚之罪，系累犯，依法应从重处罚并不适用缓刑，其归案后能如实供述犯罪事实，系坦白，依法可从轻处罚；案发后，被盗财物已追回并发还被害人，对其可酌情从轻处罚。公诉机关的量刑建议，本院予以采纳。据此，依照《中华人民共和国刑法》第二百六十四条，第六十五条第一款，第七十四条，第六十七条第三款，第五十二条，第五十三第一款之规定，判决如下： 被告人王兴毕犯盗窃罪，判处有期徒刑八个月，并处罚金人民币2500元（于判决生效后三个月内缴纳）。 （刑期从判决执行之日起计算，判决执行以前先行羁押的，羁押一日折抵刑期一日，即自2018年11月6日起至2019年7月5日止）。 如不服本判决，可在接到判决书的第二日起十日内，通过本院或者直接向云南省曲靖市中级人民法院提出上诉。书面上诉的，应当提交上诉状正本一份，副本二份。 审判长夏晓鹂 人民陪审员何盼 人民陪审员刘镔 二〇一九年一月二十二日 书记员张瑞芳", "writId": "013c43e7c589f94e7da50da50f2469c1512", "writName": "王兴毕盗窃一审刑事判决书", "inputs": {"input_ids": [756, 1298, 4689, 2146, 2014, 2356, 782, 3696, 3466, 2175, 7368, 2900, 2971, 8024, 8271, 2399, 8111, 3299, 127, 3189, 8108, 3198, 8145, 1146, 6387, 8024, 6158, 1440, 782, 4374, 1069, 3684, 1762, 671, 6775, 4507, 2146, 2014, 2356, 3173, 1266, 4991, 2458, 2518, 2146, 2014, 2356, 6004, 3441, 6125, 6887, 4638, 125, 6662, 1062, 769, 6756, 677, 8024, 4500, 7390, 6716, 3025, 2372, 4638, 1143, 4275, 1153, 2458, 733, 2145, 5882, 3378, 122, 5543, 4638, 1912, 6132, 2340, 904, 6132, 6150, 8024, 4668, 6624, 782, 3696, 2355, 8925, 1039, 8024, 1400, 4374, 1069, 3684, 1762, 6125, 2552, 5709, 1736, 4991, 1378, 678, 6756, 3198, 6158, 2146, 2014, 2356, 1062, 2128, 2229, 3696, 6356, 2831, 5815, 511, 3428, 1355, 1400, 8024, 6158, 4668, 782, 3696, 2355, 8925, 1039, 2347, 6841, 1726, 2400, 1355, 6820, 6158, 2154, 782, 5882, 3378, 122, 5543, 511, 1062, 6401, 3322, 1068, 1154, 715, 749, 4289, 6395, 510, 741, 6395, 510, 6158, 2154, 782, 7357, 6835, 510, 6158, 1440, 782, 4638, 897, 6835, 680, 6796, 6237, 510, 6795, 6371, 5011, 2497, 5023, 6395, 2141, 2900, 2971, 4638, 752, 2141, 8024, 2400, 6371, 711, 6158, 1440, 782, 4374, 1069, 3684, 809, 7478, 3791, 1304, 3300, 711, 4680, 4638, 8024, 1762, 1062, 1066, 1767, 2792, 2801, 4961, 800, 782, 6568, 4289, 8024, 1071, 6121, 711, 6239, 4306, 517, 704, 1290, 782, 3696, 1066, 1469, 1744, 1152, 3791, 518, 5018, 753, 4636, 1063, 1282, 1724, 3340, 722, 6226, 2137, 8024, 2418, 2496, 809, 4668, 4961, 5389, 6841, 4955, 1071, 1152, 752, 6569, 818, 8039, 4374, 1069, 3684, 3295, 1728, 4306, 4668, 4961, 5389, 6158, 1161, 1905, 3300, 3309, 2530, 1152, 809, 677, 1152, 5385, 8024, 1152, 5385, 2809, 6121, 2130, 3684, 809, 1400, 8024, 1762, 758, 2399, 1079, 1086, 4306, 3300, 3309, 2530, 1152, 809, 677, 1152, 5385, 722, 5389, 8024, 3221, 5168, 4306, 8024, 6844, 4500, 517, 704, 1290, 782, 3696, 1066, 1469, 1744, 1152, 3791, 518, 5018, 1063, 1282, 758, 3340, 722, 6226, 2137, 8039, 4374, 1069, 3684, 1168, 3428, 1400, 5543, 1963, 2141, 897, 6835, 5632, 2346, 4638, 5389, 6121, 8024, 5143, 1788, 4635, 8024, 6844, 4500, 517, 704, 1290, 782, 3696, 1066, 1469, 1744, 1152, 3791, 518, 5018, 1063, 1282, 673, 3340, 5018, 676, 3621, 722, 6226, 2137, 511, 2431, 2144, 704, 8024, 2456, 6379, 1161, 1905, 1071, 671, 2399, 1063, 702, 3299, 809, 678, 3300, 3309, 2530, 1152, 8024, 2400, 1905, 5385, 7032, 511, 6158, 1440, 782, 4374, 1069, 3684, 2190, 1062, 6401], "event_type_ids": [0, 0, 0, 0, 0, 0, 0, 0, 0, 0, 0, 0, 0, 0, 0, 0, 0, 0, 0, 0, 0, 0, 0, 0, 0, 0, 0, 0, 0, 0, 0, 0, 0, 0, 0, 0, 0, 0, 0, 0, 0, 0, 0, 0, 0, 0, 0, 0, 0, 0, 0, 0, 0, 0, 0, 0, 0, 0, 0, 0, 0, 0, 68, 0, 0, 0, 0, 0, 0, 0, 0, 0, 0, 0, 0, 0, 0, 0, 0, 0, 0, 0, 0, 76, 0, 0, 0, 0, 0, 0, 0, 0, 0, 0, 0, 0, 0, 0, 0, 0, 0, 0, 0, 0, 0, 0, 0, 0, 0, 0, 0, 0, 0, 0, 11, 0, 0, 0, 0, 0, 0, 76, 76, 0, 0, 0, 0, 0, 0, 0, 0, 0, 6, 0, 0, 0, 0, 0, 0, 0, 0, 0, 0, 0, 0, 0, 0, 0, 0, 0, 0, 0, 0, 0, 0, 0, 0, 0, 0, 0, 0, 0, 0, 0, 0, 3, 0, 0, 0, 0, 0, 0, 0, 0, 0, 0, 0, 0, 0, 0, 0, 0, 0, 0, 0, 0, 0, 0, 0, 0, 0, 0, 0, 0, 80, 0, 80, 0, 0, 0, 0, 0, 0, 0, 0, 0, 0, 76, 76, 0, 0, 0, 0, 0, 0, 0, 0, 0, 0, 0, 0, 0, 0, 0, 0, 0, 0, 0, 0, 0, 0, 0, 0, 0, 0, 0, 0, 0, 0, 0, 0, 0, 0, 0, 0, 0, 0, 0, 0, 0, 0, 0, 0, 0, 0, 0, 0, 0, 0, 0, 0, 0, 76, 0, 0, 0, 0, 0, 0, 0, 0, 0, 0, 0, 0, 0, 0, 0, 0, 0, 0, 0, 0, 0, 0, 0, 0, 0, 0, 0, 0, 0, 0, 0, 0, 0, 0, 0, 0, 0, 0, 0, 0, 0, 0, 0, 0, 0, 0, 0, 0, 0, 0, 0, 0, 0, 0, 0, 0, 0, 0, 0, 0, 0, 0, 0, 0, 0, 0, 0, 0, 0, 0, 0, 0, 0, 0, 3, 0, 0, 0, 0, 0, 0, 0, 0, 3, 0, 0, 0, 0, 0, 0, 0, 0, 0, 0, 0, 0, 0, 0, 0, 0, 0, 0, 0, 0, 0, 0, 0, 0, 0, 0, 0, 0, 0, 0, 0, 51, 0, 0, 0, 0, 0, 0, 0, 0, 0, 0, 0, 0, 0, 0, 0, 0, 0, 0, 0, 0, 0, 0, 0, 0, 0, 0, 0, 0, 0, 0]}}